dataspike/__init__.py
dataspike/__version__.py
dataspike/aml/__init__.py
dataspike/aml/aml.py
dataspike/aml/model.py
dataspike/applicants/__init__.py
dataspike/applicants/applicants.py
dataspike/applicants/model.py
dataspike/common.py
dataspike/dataspike.py
dataspike/documents/__init__.py
dataspike/documents/documents.py
dataspike/documents/model.py
dataspike/errors.py
dataspike/resource.py
dataspike/syncapi.py
dataspike/utils.py
dataspike/verifications/__init__.py
dataspike/verifications/model.py
dataspike/verifications/verifications.py
dataspike/VERSION
dataspike-0.1.4.dist-info/WHEEL
dataspike-0.1.4.dist-info/METADATA
dataspike-0.1.4.dist-info/RECORD
