Metadata-Version: 2.1
Name: dataspike
Version: 0.1.4
Summary: The official wrapper for Dataspike API
License: MIT
Keywords: dataspike,kyc,identity
Author-email: Sergey Rublev <sergey.rublev@dataspike.io>
Requires-Python: >=3.8
Classifier: Framework :: AsyncIO
Classifier: Intended Audience :: Developers
Classifier: Intended Audience :: Information Technology
Classifier: License :: OSI Approved :: MIT License
Classifier: Operating System :: OS Independent
Classifier: Programming Language :: Python :: 3
Classifier: Programming Language :: Python :: 3.10
Classifier: Programming Language :: Python :: 3.11
Classifier: Programming Language :: Python :: 3.8
Classifier: Programming Language :: Python :: 3.9
Classifier: Topic :: Software Development :: Libraries
Classifier: Typing :: Typed
Requires-Dist: aiohttp>=3.9.5
Requires-Dist: filetype>=1.2.0
Requires-Dist: pydantic>=2.7.1
Project-URL: Documentation, https://docs.dataspike.io
Project-URL: Homepage, https://dataspike.io
Project-URL: Repository, https://github.com/dataspike-io/docver-sdk-python
